setup.py
awsfnd_probability/Binomialdistribution.py
awsfnd_probability/Gaussiandistribution.py
awsfnd_probability/Generaldistribution.py
awsfnd_probability/__init__.py
awsfnd_probability.egg-info/PKG-INFO
awsfnd_probability.egg-info/SOURCES.txt
awsfnd_probability.egg-info/dependency_links.txt
awsfnd_probability.egg-info/not-zip-safe
awsfnd_probability.egg-info/top_level.txt