Metadata-Version: 1.0
Name: awsfnd-probability
Version: 0.1
Summary: Gaussian and Binomial distributions
Home-page: UNKNOWN
Author: Ahmad Saepulloh
Author-email: myemail@somthing.com
License: UNKNOWN
Platform: UNKNOWN
